{"type":"FeatureCollection", "features": [
{"type":"Feature","geometry":{"type":"Point","coordinates":[-80.4506,36.0115]},"properties":{"educationprogramcode":"US19103500","setting_14":6}},
{"type":"Feature","geometry":{"type":"Point","coordinates":[-80.4442,36.0064]},"properties":{"educationprogramcode":"US19103500","setting_14":6}},
{"type":"Feature","geometry":{"type":"Point","coordinates":[-80.3973,36.0294]},"properties":{"educationprogramcode":"US19103500","setting_14":11}},
{"type":"Feature","geometry":{"type":"Point","coordinates":[-80.391,36.0327]},"properties":{"educationprogramcode":"US19103500","setting_14":6}},
{"type":"Feature","geometry":{"type":"Point","coordinates":[-80.3578,36.2879]},"properties":{"educationprogramcode":"US19103500","setting_14":6}},
{"type":"Feature","geometry":{"type":"Point","coordinates":[-79.9637,36.3896]},"properties":{"educationprogramcode":"US19103500","setting_14":6}},
{"type":"Feature","geometry":{"type":"Point","coordinates":[-79.9687,36.3873]},"properties":{"educationprogramcode":"US19103500","setting_14":6}},
{"type":"Feature","geometry":{"type":"Point","coordinates":[-79.9754,36.4112]},"properties":{"educationprogramcode":"US19103500","setting_14":6}},
{"type":"Feature","geometry":{"type":"Point","coordinates":[-80.5532,35.9063]},"properties":{"educationprogramcode":"US19103500","setting_14":6}},
{"type":"Feature","geometry":{"type":"Point","coordinates":[-80.6308,36.494]},"properties":{"educationprogramcode":"US19103500","setting_14":6}},
{"type":"Feature","geometry":{"type":"Point","coordinates":[-80.2904,36.2246]},"properties":{"educationprogramcode":"US19103500","setting_14":-9}},
{"type":"Feature","geometry":{"type":"Point","coordinates":[-80.1566,36.3113]},"properties":{"educationprogramcode":"US19103500","setting_14":6}},
{"type":"Feature","geometry":{"type":"Point","coordinates":[-80.2155,36.1013]},"properties":{"educationprogramcode":"US19103500","setting_14":6}},
{"type":"Feature","geometry":{"type":"Point","coordinates":[-80.2121,36.1017]},"properties":{"educationprogramcode":"US19103500","setting_14":2}},
{"type":"Feature","geometry":{"type":"Point","coordinates":[-80.2177,36.1055]},"properties":{"educationprogramcode":"US19103500","setting_14":6}},
{"type":"Feature","geometry":{"type":"Point","coordinates":[-80.2114,36.1013]},"properties":{"educationprogramcode":"US19103500","setting_14":2}},
{"type":"Feature","geometry":{"type":"Point","coordinates":[-80.3161,36.0545]},"properties":{"educationprogramcode":"US19103500","setting_14":6}},
{"type":"Feature","geometry":{"type":"Point","coordinates":[-80.3277,36.0746]},"properties":{"educationprogramcode":"US19103500","setting_14":2}},
{"type":"Feature","geometry":{"type":"Point","coordinates":[-80.3188,36.0679]},"properties":{"educationprogramcode":"US19103500","setting_14":11}},
{"type":"Feature","geometry":{"type":"Point","coordinates":[-80.3223,36.0655]},"properties":{"educationprogramcode":"US19103500","setting_14":6}},
{"type":"Feature","geometry":{"type":"Point","coordinates":[-80.3201,36.0709]},"properties":{"educationprogramcode":"US19103500","setting_14":7}},
{"type":"Feature","geometry":{"type":"Point","coordinates":[-80.3138,36.0658]},"properties":{"educationprogramcode":"US19103500","setting_14":7}},
{"type":"Feature","geometry":{"type":"Point","coordinates":[-80.3286,36.0754]},"properties":{"educationprogramcode":"US19103500","setting_14":2}},
{"type":"Feature","geometry":{"type":"Point","coordinates":[-80.3252,36.0772]},"properties":{"educationprogramcode":"US19103500","setting_14":2}},
{"type":"Feature","geometry":{"type":"Point","coordinates":[-80.3276,36.0581]},"properties":{"educationprogramcode":"US19103500","setting_14":7}},
{"type":"Feature","geometry":{"type":"Point","coordinates":[-80.3039,36.0677]},"properties":{"educationprogramcode":"US19103500","setting_14":1}},
{"type":"Feature","geometry":{"type":"Point","coordinates":[-80.3211,36.1017]},"properties":{"educationprogramcode":"US19103500","setting_14":2}},
{"type":"Feature","geometry":{"type":"Point","coordinates":[-80.3252,36.0969]},"properties":{"educationprogramcode":"US19103500","setting_14":6}},
{"type":"Feature","geometry":{"type":"Point","coordinates":[-80.328,36.0978]},"properties":{"educationprogramcode":"US19103500","setting_14":6}},
{"type":"Feature","geometry":{"type":"Point","coordinates":[-80.3169,36.0949]},"properties":{"educationprogramcode":"US19103500","setting_14":6}},
{"type":"Feature","geometry":{"type":"Point","coordinates":[-80.3191,36.1007]},"properties":{"educationprogramcode":"US19103500","setting_14":2}},
{"type":"Feature","geometry":{"type":"Point","coordinates":[-80.3252,36.0934]},"properties":{"educationprogramcode":"US19103500","setting_14":6}},
{"type":"Feature","geometry":{"type":"Point","coordinates":[-80.3176,36.1009]},"properties":{"educationprogramcode":"US19103500","setting_14":6}},
{"type":"Feature","geometry":{"type":"Point","coordinates":[-80.2377,36.1517]},"properties":{"educationprogramcode":"US19103500","setting_14":-9}},
{"type":"Feature","geometry":{"type":"Point","coordinates":[-80.2309,36.1512]},"properties":{"educationprogramcode":"US19103500","setting_14":6}},
{"type":"Feature","geometry":{"type":"Point","coordinates":[-80.2324,36.1477]},"properties":{"educationprogramcode":"US19103500","setting_14":6}},
{"type":"Feature","geometry":{"type":"Point","coordinates":[-80.2391,36.154]},"properties":{"educationprogramcode":"US19103500","setting_14":6}},
{"type":"Feature","geometry":{"type":"Point","coordinates":[-80.2297,36.1493]},"properties":{"educationprogramcode":"US19103500","setting_14":6}},
{"type":"Feature","geometry":{"type":"Point","coordinates":[-80.2372,36.1484]},"properties":{"educationprogramcode":"US19103500","setting_14":6}},
{"type":"Feature","geometry":{"type":"Point","coordinates":[-80.3284,36.1432]},"properties":{"educationprogramcode":"US19103500","setting_14":12}},
{"type":"Feature","geometry":{"type":"Point","coordinates":[-80.3273,36.1485]},"properties":{"educationprogramcode":"US19103500","setting_14":6}},
{"type":"Feature","geometry":{"type":"Point","coordinates":[-80.3257,36.1498]},"properties":{"educationprogramcode":"US19103500","setting_14":11}},
{"type":"Feature","geometry":{"type":"Point","coordinates":[-80.329,36.1448]},"properties":{"educationprogramcode":"US19103500","setting_14":6}},
{"type":"Feature","geometry":{"type":"Point","coordinates":[-80.3197,36.1503]},"properties":{"educationprogramcode":"US19103500","setting_14":6}},
{"type":"Feature","geometry":{"type":"Point","coordinates":[-80.3171,36.1524]},"properties":{"educationprogramcode":"US19103500","setting_14":11}},
{"type":"Feature","geometry":{"type":"Point","coordinates":[-80.3168,36.1497]},"properties":{"educationprogramcode":"US19103500","setting_14":6}},
{"type":"Feature","geometry":{"type":"Point","coordinates":[-80.3241,36.1506]},"properties":{"educationprogramcode":"US19103500","setting_14":6}},
{"type":"Feature","geometry":{"type":"Point","coordinates":[-80.3252,36.1495]},"properties":{"educationprogramcode":"US19103500","setting_14":6}},
{"type":"Feature","geometry":{"type":"Point","coordinates":[-80.3229,36.1502]},"properties":{"educationprogramcode":"US19103500","setting_14":6}},
{"type":"Feature","geometry":{"type":"Point","coordinates":[-80.1849,36.0674]},"properties":{"educationprogramcode":"US19103500","setting_14":-9}},
{"type":"Feature","geometry":{"type":"Point","coordinates":[-80.1803,36.061]},"properties":{"educationprogramcode":"US19103500","setting_14":11}},
{"type":"Feature","geometry":{"type":"Point","coordinates":[-80.2426,36.1029]},"properties":{"educationprogramcode":"US19103500","setting_14":-9}},
{"type":"Feature","geometry":{"type":"Point","coordinates":[-80.2434,36.1021]},"properties":{"educationprogramcode":"US19103500","setting_14":-9}},
{"type":"Feature","geometry":{"type":"Point","coordinates":[-80.2644,36.0418]},"properties":{"educationprogramcode":"US19103500","setting_14":11}},
{"type":"Feature","geometry":{"type":"Point","coordinates":[-79.8264,35.6565]},"properties":{"educationprogramcode":"US19103500","setting_14":-9}},
{"type":"Feature","geometry":{"type":"Point","coordinates":[-79.8351,35.6549]},"properties":{"educationprogramcode":"US19103500","setting_14":6}},
{"type":"Feature","geometry":{"type":"Point","coordinates":[-79.8299,35.6531]},"properties":{"educationprogramcode":"US19103500","setting_14":6}},
{"type":"Feature","geometry":{"type":"Point","coordinates":[-79.8095,35.6665]},"properties":{"educationprogramcode":"US19103500","setting_14":-9}},
{"type":"Feature","geometry":{"type":"Point","coordinates":[-79.494,36.0309]},"properties":{"educationprogramcode":"US19103500","setting_14":6}},
{"type":"Feature","geometry":{"type":"Point","coordinates":[-79.4851,36.0381]},"properties":{"educationprogramcode":"US19103500","setting_14":6}},
{"type":"Feature","geometry":{"type":"Point","coordinates":[-79.484,36.0277]},"properties":{"educationprogramcode":"US19103500","setting_14":6}},
{"type":"Feature","geometry":{"type":"Point","coordinates":[-79.4897,36.0409]},"properties":{"educationprogramcode":"US19103500","setting_14":6}},
{"type":"Feature","geometry":{"type":"Point","coordinates":[-79.4836,36.0348]},"properties":{"educationprogramcode":"US19103500","setting_14":6}},
{"type":"Feature","geometry":{"type":"Point","coordinates":[-79.4893,36.0297]},"properties":{"educationprogramcode":"US19103500","setting_14":6}},
{"type":"Feature","geometry":{"type":"Point","coordinates":[-79.4129,36.1298]},"properties":{"educationprogramcode":"US19103500","setting_14":6}},
{"type":"Feature","geometry":{"type":"Point","coordinates":[-79.4155,36.1309]},"properties":{"educationprogramcode":"US19103500","setting_14":6}},
{"type":"Feature","geometry":{"type":"Point","coordinates":[-79.4159,36.1291]},"properties":{"educationprogramcode":"US19103500","setting_14":6}},
{"type":"Feature","geometry":{"type":"Point","coordinates":[-79.4171,36.1291]},"properties":{"educationprogramcode":"US19103500","setting_14":6}},
{"type":"Feature","geometry":{"type":"Point","coordinates":[-79.4182,36.1283]},"properties":{"educationprogramcode":"US19103500","setting_14":7}},
{"type":"Feature","geometry":{"type":"Point","coordinates":[-79.4147,36.1279]},"properties":{"educationprogramcode":"US19103500","setting_14":6}},
{"type":"Feature","geometry":{"type":"Point","coordinates":[-79.4201,36.1298]},"properties":{"educationprogramcode":"US19103500","setting_14":6}},
{"type":"Feature","geometry":{"type":"Point","coordinates":[-79.4189,36.1264]},"properties":{"educationprogramcode":"US19103500","setting_14":6}},
{"type":"Feature","geometry":{"type":"Point","coordinates":[-79.4172,36.1319]},"properties":{"educationprogramcode":"US19103500","setting_14":6}},
{"type":"Feature","geometry":{"type":"Point","coordinates":[-80.0081,36.0981]},"properties":{"educationprogramcode":"US19103500","setting_14":6}},
{"type":"Feature","geometry":{"type":"Point","coordinates":[-80.0112,36.0974]},"properties":{"educationprogramcode":"US19103500","setting_14":6}},
{"type":"Feature","geometry":{"type":"Point","coordinates":[-80.0076,36.0984]},"properties":{"educationprogramcode":"US19103500","setting_14":6}},
{"type":"Feature","geometry":{"type":"Point","coordinates":[-80.0103,36.1007]},"properties":{"educationprogramcode":"US19103500","setting_14":6}},
{"type":"Feature","geometry":{"type":"Point","coordinates":[-80.0113,36.0985]},"properties":{"educationprogramcode":"US19103500","setting_14":6}},
{"type":"Feature","geometry":{"type":"Point","coordinates":[-80.1085,35.6162]},"properties":{"educationprogramcode":"US19103500","setting_14":6}},
{"type":"Feature","geometry":{"type":"Point","coordinates":[-79.5871,36.1282]},"properties":{"educationprogramcode":"US19103500","setting_14":6}},
{"type":"Feature","geometry":{"type":"Point","coordinates":[-79.3639,36.0247]},"properties":{"educationprogramcode":"US19103500","setting_14":7}},
{"type":"Feature","geometry":{"type":"Point","coordinates":[-79.371,36.0202]},"properties":{"educationprogramcode":"US19103500","setting_14":6}},
{"type":"Feature","geometry":{"type":"Point","coordinates":[-79.9973,35.9697]},"properties":{"educationprogramcode":"US19103500","setting_14":6}},
{"type":"Feature","geometry":{"type":"Point","coordinates":[-80.003,35.9714]},"properties":{"educationprogramcode":"US19103500","setting_14":6}},
{"type":"Feature","geometry":{"type":"Point","coordinates":[-80.0016,35.9705]},"properties":{"educationprogramcode":"US19103500","setting_14":6}},
{"type":"Feature","geometry":{"type":"Point","coordinates":[-80.0003,35.9666]},"properties":{"educationprogramcode":"US19103500","setting_14":6}},
{"type":"Feature","geometry":{"type":"Point","coordinates":[-80.0025,35.9659]},"properties":{"educationprogramcode":"US19103500","setting_14":9}},
{"type":"Feature","geometry":{"type":"Point","coordinates":[-80.001,35.9653]},"properties":{"educationprogramcode":"US19103500","setting_14":6}},
{"type":"Feature","geometry":{"type":"Point","coordinates":[-79.9984,35.967]},"properties":{"educationprogramcode":"US19103500","setting_14":7}},
{"type":"Feature","geometry":{"type":"Point","coordinates":[-80.0015,35.9775]},"properties":{"educationprogramcode":"US19103500","setting_14":4}},
{"type":"Feature","geometry":{"type":"Point","coordinates":[-80.035,35.9545]},"properties":{"educationprogramcode":"US19103500","setting_14":11}},
{"type":"Feature","geometry":{"type":"Point","coordinates":[-80.0405,35.9531]},"properties":{"educationprogramcode":"US19103500","setting_14":6}},
{"type":"Feature","geometry":{"type":"Point","coordinates":[-80.036,35.9588]},"properties":{"educationprogramcode":"US19103500","setting_14":6}},
{"type":"Feature","geometry":{"type":"Point","coordinates":[-80.0451,35.9572]},"properties":{"educationprogramcode":"US19103500","setting_14":6}},
{"type":"Feature","geometry":{"type":"Point","coordinates":[-80.0435,35.9599]},"properties":{"educationprogramcode":"US19103500","setting_14":11}},
{"type":"Feature","geometry":{"type":"Point","coordinates":[-80.0433,35.9532]},"properties":{"educationprogramcode":"US19103500","setting_14":6}},
{"type":"Feature","geometry":{"type":"Point","coordinates":[-79.9771,35.9059]},"properties":{"educationprogramcode":"US19103500","setting_14":6}},
{"type":"Feature","geometry":{"type":"Point","coordinates":[-79.9768,35.911]},"properties":{"educationprogramcode":"US19103500","setting_14":6}},
{"type":"Feature","geometry":{"type":"Point","coordinates":[-79.9976,36.0071]},"properties":{"educationprogramcode":"US19103500","setting_14":2}},
{"type":"Feature","geometry":{"type":"Point","coordinates":[-80.0049,36.0154]},"properties":{"educationprogramcode":"US19103500","setting_14":7}},
{"type":"Feature","geometry":{"type":"Point","coordinates":[-80.0029,36.006]},"properties":{"educationprogramcode":"US19103500","setting_14":-9}},
{"type":"Feature","geometry":{"type":"Point","coordinates":[-79.9314,35.996]},"properties":{"educationprogramcode":"US19103500","setting_14":6}},
{"type":"Feature","geometry":{"type":"Point","coordinates":[-79.9288,36.001]},"properties":{"educationprogramcode":"US19103500","setting_14":6}},
{"type":"Feature","geometry":{"type":"Point","coordinates":[-80.0896,36.1217]},"properties":{"educationprogramcode":"US19103500","setting_14":2}},
{"type":"Feature","geometry":{"type":"Point","coordinates":[-80.0989,36.1206]},"properties":{"educationprogramcode":"US19103500","setting_14":11}},
{"type":"Feature","geometry":{"type":"Point","coordinates":[-80.0889,36.1196]},"properties":{"educationprogramcode":"US19103500","setting_14":6}},
{"type":"Feature","geometry":{"type":"Point","coordinates":[-80.0908,36.1168]},"properties":{"educationprogramcode":"US19103500","setting_14":-9}},
{"type":"Feature","geometry":{"type":"Point","coordinates":[-80.0918,36.1192]},"properties":{"educationprogramcode":"US19103500","setting_14":11}},
{"type":"Feature","geometry":{"type":"Point","coordinates":[-80.0916,36.1097]},"properties":{"educationprogramcode":"US19103500","setting_14":6}},
{"type":"Feature","geometry":{"type":"Point","coordinates":[-80.2817,35.8211]},"properties":{"educationprogramcode":"US19103500","setting_14":6}},
{"type":"Feature","geometry":{"type":"Point","coordinates":[-80.2811,35.8236]},"properties":{"educationprogramcode":"US19103500","setting_14":6}},
{"type":"Feature","geometry":{"type":"Point","coordinates":[-80.2756,35.8272]},"properties":{"educationprogramcode":"US19103500","setting_14":6}},
{"type":"Feature","geometry":{"type":"Point","coordinates":[-80.2794,35.8258]},"properties":{"educationprogramcode":"US19103500","setting_14":6}},
{"type":"Feature","geometry":{"type":"Point","coordinates":[-80.2578,35.8076]},"properties":{"educationprogramcode":"US19103500","setting_14":-9}},
{"type":"Feature","geometry":{"type":"Point","coordinates":[-80.2624,35.8116]},"properties":{"educationprogramcode":"US19103500","setting_14":6}},
{"type":"Feature","geometry":{"type":"Point","coordinates":[-79.674,36.1158]},"properties":{"educationprogramcode":"US19103500","setting_14":6}},
{"type":"Feature","geometry":{"type":"Point","coordinates":[-79.7602,35.9549]},"properties":{"educationprogramcode":"US19103500","setting_14":6}},
{"type":"Feature","geometry":{"type":"Point","coordinates":[-79.7568,35.9518]},"properties":{"educationprogramcode":"US19103500","setting_14":6}},
{"type":"Feature","geometry":{"type":"Point","coordinates":[-79.7575,35.952]},"properties":{"educationprogramcode":"US19103500","setting_14":6}},
{"type":"Feature","geometry":{"type":"Point","coordinates":[-79.619,36.3539]},"properties":{"educationprogramcode":"US19103500","setting_14":-9}},
{"type":"Feature","geometry":{"type":"Point","coordinates":[-79.5897,36.4507]},"properties":{"educationprogramcode":"US19103500","setting_14":-9}},
{"type":"Feature","geometry":{"type":"Point","coordinates":[-79.9842,36.2387]},"properties":{"educationprogramcode":"US19103500","setting_14":6}},
{"type":"Feature","geometry":{"type":"Point","coordinates":[-79.9837,36.2407]},"properties":{"educationprogramcode":"US19103500","setting_14":6}},
{"type":"Feature","geometry":{"type":"Point","coordinates":[-79.8962,36.2]},"properties":{"educationprogramcode":"US19103500","setting_14":2}},
{"type":"Feature","geometry":{"type":"Point","coordinates":[-80.085,35.8836]},"properties":{"educationprogramcode":"US19103500","setting_14":6}},
{"type":"Feature","geometry":{"type":"Point","coordinates":[-80.0805,35.8859]},"properties":{"educationprogramcode":"US19103500","setting_14":6}},
{"type":"Feature","geometry":{"type":"Point","coordinates":[-80.0875,35.8812]},"properties":{"educationprogramcode":"US19103500","setting_14":1}},
{"type":"Feature","geometry":{"type":"Point","coordinates":[-79.946,35.8694]},"properties":{"educationprogramcode":"US19103500","setting_14":6}},
{"type":"Feature","geometry":{"type":"Point","coordinates":[-79.3353,36.4046]},"properties":{"educationprogramcode":"US19103500","setting_14":6}},
{"type":"Feature","geometry":{"type":"Point","coordinates":[-79.7617,36.0735]},"properties":{"educationprogramcode":"US19103500","setting_14":2}},
{"type":"Feature","geometry":{"type":"Point","coordinates":[-79.7651,36.0651]},"properties":{"educationprogramcode":"US19103500","setting_14":6}},
{"type":"Feature","geometry":{"type":"Point","coordinates":[-79.7785,36.0712]},"properties":{"educationprogramcode":"US19103500","setting_14":9}},
{"type":"Feature","geometry":{"type":"Point","coordinates":[-79.8276,36.0643]},"properties":{"educationprogramcode":"US19103500","setting_14":6}},
{"type":"Feature","geometry":{"type":"Point","coordinates":[-79.7347,36.1082]},"properties":{"educationprogramcode":"US19103500","setting_14":6}},
{"type":"Feature","geometry":{"type":"Point","coordinates":[-79.7435,36.1125]},"properties":{"educationprogramcode":"US19103500","setting_14":-9}},
{"type":"Feature","geometry":{"type":"Point","coordinates":[-79.7388,36.1147]},"properties":{"educationprogramcode":"US19103500","setting_14":6}},
{"type":"Feature","geometry":{"type":"Point","coordinates":[-79.7462,36.1103]},"properties":{"educationprogramcode":"US19103500","setting_14":6}},
{"type":"Feature","geometry":{"type":"Point","coordinates":[-79.7613,36.0188]},"properties":{"educationprogramcode":"US19103500","setting_14":6}},
{"type":"Feature","geometry":{"type":"Point","coordinates":[-79.7684,36.024]},"properties":{"educationprogramcode":"US19103500","setting_14":11}},
{"type":"Feature","geometry":{"type":"Point","coordinates":[-79.7679,36.0162]},"properties":{"educationprogramcode":"US19103500","setting_14":6}},
{"type":"Feature","geometry":{"type":"Point","coordinates":[-79.7745,36.0227]},"properties":{"educationprogramcode":"US19103500","setting_14":-9}},
{"type":"Feature","geometry":{"type":"Point","coordinates":[-79.7742,36.0274]},"properties":{"educationprogramcode":"US19103500","setting_14":6}},
{"type":"Feature","geometry":{"type":"Point","coordinates":[-79.7639,36.0156]},"properties":{"educationprogramcode":"US19103500","setting_14":6}},
{"type":"Feature","geometry":{"type":"Point","coordinates":[-79.7717,36.0222]},"properties":{"educationprogramcode":"US19103500","setting_14":6}},
{"type":"Feature","geometry":{"type":"Point","coordinates":[-79.7634,36.025]},"properties":{"educationprogramcode":"US19103500","setting_14":6}},
{"type":"Feature","geometry":{"type":"Point","coordinates":[-79.7699,36.0214]},"properties":{"educationprogramcode":"US19103500","setting_14":6}},
{"type":"Feature","geometry":{"type":"Point","coordinates":[-79.7712,36.021]},"properties":{"educationprogramcode":"US19103500","setting_14":6}},
{"type":"Feature","geometry":{"type":"Point","coordinates":[-79.8699,36.0085]},"properties":{"educationprogramcode":"US19103500","setting_14":6}},
{"type":"Feature","geometry":{"type":"Point","coordinates":[-79.864,36.0128]},"properties":{"educationprogramcode":"US19103500","setting_14":2}},
{"type":"Feature","geometry":{"type":"Point","coordinates":[-79.8678,36.0093]},"properties":{"educationprogramcode":"US19103500","setting_14":7}},
{"type":"Feature","geometry":{"type":"Point","coordinates":[-79.866,36.0169]},"properties":{"educationprogramcode":"US19103500","setting_14":7}},
{"type":"Feature","geometry":{"type":"Point","coordinates":[-79.8661,36.0138]},"properties":{"educationprogramcode":"US19103500","setting_14":6}},
{"type":"Feature","geometry":{"type":"Point","coordinates":[-79.8711,36.0151]},"properties":{"educationprogramcode":"US19103500","setting_14":6}},
{"type":"Feature","geometry":{"type":"Point","coordinates":[-79.8698,36.0158]},"properties":{"educationprogramcode":"US19103500","setting_14":6}},
{"type":"Feature","geometry":{"type":"Point","coordinates":[-79.8683,36.0128]},"properties":{"educationprogramcode":"US19103500","setting_14":6}},
{"type":"Feature","geometry":{"type":"Point","coordinates":[-79.8134,36.1078]},"properties":{"educationprogramcode":"US19103500","setting_14":6}},
{"type":"Feature","geometry":{"type":"Point","coordinates":[-79.9311,36.0932]},"properties":{"educationprogramcode":"US19103500","setting_14":-9}},
{"type":"Feature","geometry":{"type":"Point","coordinates":[-79.8883,36.0974]},"properties":{"educationprogramcode":"US19103500","setting_14":6}},
{"type":"Feature","geometry":{"type":"Point","coordinates":[-79.8873,36.0989]},"properties":{"educationprogramcode":"US19103500","setting_14":6}},
{"type":"Feature","geometry":{"type":"Point","coordinates":[-79.8843,36.0936]},"properties":{"educationprogramcode":"US19103500","setting_14":6}},
{"type":"Feature","geometry":{"type":"Point","coordinates":[-79.8837,36.0919]},"properties":{"educationprogramcode":"US19103500","setting_14":6}},
{"type":"Feature","geometry":{"type":"Point","coordinates":[-79.8893,36.0999]},"properties":{"educationprogramcode":"US19103500","setting_14":6}},
{"type":"Feature","geometry":{"type":"Point","coordinates":[-79.8846,36.0929]},"properties":{"educationprogramcode":"US19103500","setting_14":11}},
{"type":"Feature","geometry":{"type":"Point","coordinates":[-79.8794,36.0991]},"properties":{"educationprogramcode":"US19103500","setting_14":6}},
{"type":"Feature","geometry":{"type":"Point","coordinates":[-79.8097,36.1593]},"properties":{"educationprogramcode":"US19103500","setting_14":6}},
{"type":"Feature","geometry":{"type":"Point","coordinates":[-79.8156,36.1514]},"properties":{"educationprogramcode":"US19103500","setting_14":6}},
{"type":"Feature","geometry":{"type":"Point","coordinates":[-79.8165,36.1536]},"properties":{"educationprogramcode":"US19103500","setting_14":6}},
{"type":"Feature","geometry":{"type":"Point","coordinates":[-79.0437,35.9462]},"properties":{"educationprogramcode":"US19103500","setting_14":11}},
{"type":"Feature","geometry":{"type":"Point","coordinates":[-78.6888,36.1206]},"properties":{"educationprogramcode":"US19103500","setting_14":7}},
{"type":"Feature","geometry":{"type":"Point","coordinates":[-78.4243,35.4472]},"properties":{"educationprogramcode":"US19103500","setting_14":-9}},
{"type":"Feature","geometry":{"type":"Point","coordinates":[-78.7009,35.7976]},"properties":{"educationprogramcode":"US19103500","setting_14":11}},
{"type":"Feature","geometry":{"type":"Point","coordinates":[-78.6982,35.8105]},"properties":{"educationprogramcode":"US19103500","setting_14":7}},
{"type":"Feature","geometry":{"type":"Point","coordinates":[-78.9484,36.0206]},"properties":{"educationprogramcode":"US19103500","setting_14":2}},
{"type":"Feature","geometry":{"type":"Point","coordinates":[-78.9406,35.9686]},"properties":{"educationprogramcode":"US19103500","setting_14":7}},
{"type":"Feature","geometry":{"type":"Point","coordinates":[-77.9128,35.7333]},"properties":{"educationprogramcode":"US19103500","setting_14":6}},
{"type":"Feature","geometry":{"type":"Point","coordinates":[-80.4722,35.6617]},"properties":{"educationprogramcode":"US19103500","setting_14":6}},
{"type":"Feature","geometry":{"type":"Point","coordinates":[-80.4309,35.6264]},"properties":{"educationprogramcode":"US19103500","setting_14":6}},
{"type":"Feature","geometry":{"type":"Point","coordinates":[-80.4321,35.6958]},"properties":{"educationprogramcode":"US19103500","setting_14":6}},
{"type":"Feature","geometry":{"type":"Point","coordinates":[-80.7384,35.3139]},"properties":{"educationprogramcode":"US19103500","setting_14":7}},
{"type":"Feature","geometry":{"type":"Point","coordinates":[-78.9767,35.0336]},"properties":{"educationprogramcode":"US19103500","setting_14":12}},
{"type":"Feature","geometry":{"type":"Point","coordinates":[-78.8662,35.0673]},"properties":{"educationprogramcode":"US19103500","setting_14":6}},
{"type":"Feature","geometry":{"type":"Point","coordinates":[-77.9314,34.2231]},"properties":{"educationprogramcode":"US19103500","setting_14":2}},
{"type":"Feature","geometry":{"type":"Point","coordinates":[-78.167,34.0355]},"properties":{"educationprogramcode":"US19103500","setting_14":6}},
{"type":"Feature","geometry":{"type":"Point","coordinates":[-77.9321,34.5517]},"properties":{"educationprogramcode":"US19103500","setting_14":9}},
{"type":"Feature","geometry":{"type":"Point","coordinates":[-77.5495,35.4257]},"properties":{"educationprogramcode":"US19103500","setting_14":9}},
{"type":"Feature","geometry":{"type":"Point","coordinates":[-77.3773,34.7775]},"properties":{"educationprogramcode":"US19103500","setting_14":6}},
{"type":"Feature","geometry":{"type":"Point","coordinates":[-80.8139,36.3171]},"properties":{"educationprogramcode":"US19103500","setting_14":-9}},
{"type":"Feature","geometry":{"type":"Point","coordinates":[-80.815,36.3144]},"properties":{"educationprogramcode":"US19103500","setting_14":1}}
]}