{"type":"FeatureCollection", "features": [
{"type":"Feature","geometry":{"type":"Point","coordinates":[-79.775,36.0733]},"properties":{"educationprogramcode":"US19403900","setting_14":1}},
{"type":"Feature","geometry":{"type":"Point","coordinates":[-78.3494,35.5167]},"properties":{"educationprogramcode":"US19403900","setting_14":1}},
{"type":"Feature","geometry":{"type":"Point","coordinates":[-81.0369,35.2431]},"properties":{"educationprogramcode":"US19403900","setting_14":1}},
{"type":"Feature","geometry":{"type":"Point","coordinates":[-81.0359,35.2415]},"properties":{"educationprogramcode":"US19403900","setting_14":6}},
{"type":"Feature","geometry":{"type":"Point","coordinates":[-81.0323,35.2416]},"properties":{"educationprogramcode":"US19403900","setting_14":1}},
{"type":"Feature","geometry":{"type":"Point","coordinates":[-81.0403,35.2459]},"properties":{"educationprogramcode":"US19403900","setting_14":11}},
{"type":"Feature","geometry":{"type":"Point","coordinates":[-81.2833,35.2872]},"properties":{"educationprogramcode":"US19403900","setting_14":6}},
{"type":"Feature","geometry":{"type":"Point","coordinates":[-81.2809,35.2845]},"properties":{"educationprogramcode":"US19403900","setting_14":3}},
{"type":"Feature","geometry":{"type":"Point","coordinates":[-81.2806,35.2856]},"properties":{"educationprogramcode":"US19403900","setting_14":1}},
{"type":"Feature","geometry":{"type":"Point","coordinates":[-81.3776,35.3793]},"properties":{"educationprogramcode":"US19403900","setting_14":-9}},
{"type":"Feature","geometry":{"type":"Point","coordinates":[-80.6464,35.4137]},"properties":{"educationprogramcode":"US19403900","setting_14":6}},
{"type":"Feature","geometry":{"type":"Point","coordinates":[-80.6527,35.4095]},"properties":{"educationprogramcode":"US19403900","setting_14":11}},
{"type":"Feature","geometry":{"type":"Point","coordinates":[-80.8644,35.4815]},"properties":{"educationprogramcode":"US19403900","setting_14":6}},
{"type":"Feature","geometry":{"type":"Point","coordinates":[-81.1818,35.3288]},"properties":{"educationprogramcode":"US19403900","setting_14":7}},
{"type":"Feature","geometry":{"type":"Point","coordinates":[-81.1831,35.3259]},"properties":{"educationprogramcode":"US19403900","setting_14":1}},
{"type":"Feature","geometry":{"type":"Point","coordinates":[-81.1765,35.3299]},"properties":{"educationprogramcode":"US19403900","setting_14":2}},
{"type":"Feature","geometry":{"type":"Point","coordinates":[-81.0205,35.5115]},"properties":{"educationprogramcode":"US19403900","setting_14":11}},
{"type":"Feature","geometry":{"type":"Point","coordinates":[-81.0202,35.5098]},"properties":{"educationprogramcode":"US19403900","setting_14":1}},
{"type":"Feature","geometry":{"type":"Point","coordinates":[-81.019,35.5068]},"properties":{"educationprogramcode":"US19403900","setting_14":2}},
{"type":"Feature","geometry":{"type":"Point","coordinates":[-81.866,35.3315]},"properties":{"educationprogramcode":"US19403900","setting_14":-9}},
{"type":"Feature","geometry":{"type":"Point","coordinates":[-81.2411,35.2314]},"properties":{"educationprogramcode":"US19403900","setting_14":6}},
{"type":"Feature","geometry":{"type":"Point","coordinates":[-81.2406,35.2307]},"properties":{"educationprogramcode":"US19403900","setting_14":7}},
{"type":"Feature","geometry":{"type":"Point","coordinates":[-81.244,35.2289]},"properties":{"educationprogramcode":"US19403900","setting_14":2}},
{"type":"Feature","geometry":{"type":"Point","coordinates":[-81.2391,35.2244]},"properties":{"educationprogramcode":"US19403900","setting_14":11}},
{"type":"Feature","geometry":{"type":"Point","coordinates":[-81.2375,35.1938]},"properties":{"educationprogramcode":"US19403900","setting_14":1}},
{"type":"Feature","geometry":{"type":"Point","coordinates":[-81.2362,35.194]},"properties":{"educationprogramcode":"US19403900","setting_14":1}},
{"type":"Feature","geometry":{"type":"Point","coordinates":[-81.2341,35.1921]},"properties":{"educationprogramcode":"US19403900","setting_14":1}},
{"type":"Feature","geometry":{"type":"Point","coordinates":[-81.1438,35.2392]},"properties":{"educationprogramcode":"US19403900","setting_14":1}},
{"type":"Feature","geometry":{"type":"Point","coordinates":[-81.1507,35.2254]},"properties":{"educationprogramcode":"US19403900","setting_14":1}},
{"type":"Feature","geometry":{"type":"Point","coordinates":[-81.1415,35.2229]},"properties":{"educationprogramcode":"US19403900","setting_14":6}},
{"type":"Feature","geometry":{"type":"Point","coordinates":[-81.1352,35.2208]},"properties":{"educationprogramcode":"US19403900","setting_14":1}},
{"type":"Feature","geometry":{"type":"Point","coordinates":[-81.1513,35.2365]},"properties":{"educationprogramcode":"US19403900","setting_14":1}},
{"type":"Feature","geometry":{"type":"Point","coordinates":[-81.1447,35.2243]},"properties":{"educationprogramcode":"US19403900","setting_14":1}},
{"type":"Feature","geometry":{"type":"Point","coordinates":[-81.1395,35.2218]},"properties":{"educationprogramcode":"US19403900","setting_14":6}},
{"type":"Feature","geometry":{"type":"Point","coordinates":[-81.1409,35.228]},"properties":{"educationprogramcode":"US19403900","setting_14":1}},
{"type":"Feature","geometry":{"type":"Point","coordinates":[-81.149,35.2279]},"properties":{"educationprogramcode":"US19403900","setting_14":1}},
{"type":"Feature","geometry":{"type":"Point","coordinates":[-81.1365,35.2268]},"properties":{"educationprogramcode":"US19403900","setting_14":1}},
{"type":"Feature","geometry":{"type":"Point","coordinates":[-81.1415,35.2311]},"properties":{"educationprogramcode":"US19403900","setting_14":1}},
{"type":"Feature","geometry":{"type":"Point","coordinates":[-81.1519,35.2248]},"properties":{"educationprogramcode":"US19403900","setting_14":1}},
{"type":"Feature","geometry":{"type":"Point","coordinates":[-81.1456,35.2265]},"properties":{"educationprogramcode":"US19403900","setting_14":1}},
{"type":"Feature","geometry":{"type":"Point","coordinates":[-81.1473,35.2261]},"properties":{"educationprogramcode":"US19403900","setting_14":1}},
{"type":"Feature","geometry":{"type":"Point","coordinates":[-81.1398,35.224]},"properties":{"educationprogramcode":"US19403900","setting_14":1}},
{"type":"Feature","geometry":{"type":"Point","coordinates":[-81.1434,35.2249]},"properties":{"educationprogramcode":"US19403900","setting_14":1}},
{"type":"Feature","geometry":{"type":"Point","coordinates":[-81.1414,35.2362]},"properties":{"educationprogramcode":"US19403900","setting_14":1}},
{"type":"Feature","geometry":{"type":"Point","coordinates":[-81.1335,35.2215]},"properties":{"educationprogramcode":"US19403900","setting_14":1}},
{"type":"Feature","geometry":{"type":"Point","coordinates":[-81.1352,35.2384]},"properties":{"educationprogramcode":"US19403900","setting_14":6}},
{"type":"Feature","geometry":{"type":"Point","coordinates":[-81.1368,35.2363]},"properties":{"educationprogramcode":"US19403900","setting_14":1}},
{"type":"Feature","geometry":{"type":"Point","coordinates":[-81.1511,35.237]},"properties":{"educationprogramcode":"US19403900","setting_14":1}},
{"type":"Feature","geometry":{"type":"Point","coordinates":[-81.1506,35.2308]},"properties":{"educationprogramcode":"US19403900","setting_14":1}},
{"type":"Feature","geometry":{"type":"Point","coordinates":[-81.1406,35.2236]},"properties":{"educationprogramcode":"US19403900","setting_14":1}},
{"type":"Feature","geometry":{"type":"Point","coordinates":[-81.1365,35.2391]},"properties":{"educationprogramcode":"US19403900","setting_14":1}},
{"type":"Feature","geometry":{"type":"Point","coordinates":[-81.1406,35.2303]},"properties":{"educationprogramcode":"US19403900","setting_14":1}},
{"type":"Feature","geometry":{"type":"Point","coordinates":[-81.1364,35.238]},"properties":{"educationprogramcode":"US19403900","setting_14":7}},
{"type":"Feature","geometry":{"type":"Point","coordinates":[-81.1346,35.235]},"properties":{"educationprogramcode":"US19403900","setting_14":1}},
{"type":"Feature","geometry":{"type":"Point","coordinates":[-81.1416,35.2252]},"properties":{"educationprogramcode":"US19403900","setting_14":6}},
{"type":"Feature","geometry":{"type":"Point","coordinates":[-81.1451,35.227]},"properties":{"educationprogramcode":"US19403900","setting_14":12}},
{"type":"Feature","geometry":{"type":"Point","coordinates":[-81.1431,35.2327]},"properties":{"educationprogramcode":"US19403900","setting_14":1}},
{"type":"Feature","geometry":{"type":"Point","coordinates":[-81.1472,35.2222]},"properties":{"educationprogramcode":"US19403900","setting_14":1}},
{"type":"Feature","geometry":{"type":"Point","coordinates":[-81.1409,35.2311]},"properties":{"educationprogramcode":"US19403900","setting_14":2}},
{"type":"Feature","geometry":{"type":"Point","coordinates":[-81.1491,35.2315]},"properties":{"educationprogramcode":"US19403900","setting_14":1}},
{"type":"Feature","geometry":{"type":"Point","coordinates":[-81.14,35.2232]},"properties":{"educationprogramcode":"US19403900","setting_14":1}},
{"type":"Feature","geometry":{"type":"Point","coordinates":[-81.1383,35.2351]},"properties":{"educationprogramcode":"US19403900","setting_14":11}},
{"type":"Feature","geometry":{"type":"Point","coordinates":[-81.1452,35.2219]},"properties":{"educationprogramcode":"US19403900","setting_14":1}},
{"type":"Feature","geometry":{"type":"Point","coordinates":[-81.1505,35.2246]},"properties":{"educationprogramcode":"US19403900","setting_14":1}},
{"type":"Feature","geometry":{"type":"Point","coordinates":[-81.1379,35.2233]},"properties":{"educationprogramcode":"US19403900","setting_14":6}},
{"type":"Feature","geometry":{"type":"Point","coordinates":[-81.1337,35.2321]},"properties":{"educationprogramcode":"US19403900","setting_14":1}},
{"type":"Feature","geometry":{"type":"Point","coordinates":[-81.1437,35.2236]},"properties":{"educationprogramcode":"US19403900","setting_14":1}},
{"type":"Feature","geometry":{"type":"Point","coordinates":[-81.1403,35.224]},"properties":{"educationprogramcode":"US19403900","setting_14":1}},
{"type":"Feature","geometry":{"type":"Point","coordinates":[-81.1358,35.2246]},"properties":{"educationprogramcode":"US19403900","setting_14":-9}},
{"type":"Feature","geometry":{"type":"Point","coordinates":[-81.144,35.2232]},"properties":{"educationprogramcode":"US19403900","setting_14":1}},
{"type":"Feature","geometry":{"type":"Point","coordinates":[-81.1355,35.2275]},"properties":{"educationprogramcode":"US19403900","setting_14":6}},
{"type":"Feature","geometry":{"type":"Point","coordinates":[-81.1493,35.2253]},"properties":{"educationprogramcode":"US19403900","setting_14":1}},
{"type":"Feature","geometry":{"type":"Point","coordinates":[-81.1411,35.221]},"properties":{"educationprogramcode":"US19403900","setting_14":1}},
{"type":"Feature","geometry":{"type":"Point","coordinates":[-81.146,35.2373]},"properties":{"educationprogramcode":"US19403900","setting_14":1}},
{"type":"Feature","geometry":{"type":"Point","coordinates":[-81.1366,35.2304]},"properties":{"educationprogramcode":"US19403900","setting_14":1}},
{"type":"Feature","geometry":{"type":"Point","coordinates":[-81.1471,35.239]},"properties":{"educationprogramcode":"US19403900","setting_14":1}},
{"type":"Feature","geometry":{"type":"Point","coordinates":[-81.1331,35.2257]},"properties":{"educationprogramcode":"US19403900","setting_14":11}},
{"type":"Feature","geometry":{"type":"Point","coordinates":[-81.151,35.2301]},"properties":{"educationprogramcode":"US19403900","setting_14":1}},
{"type":"Feature","geometry":{"type":"Point","coordinates":[-81.1368,35.2368]},"properties":{"educationprogramcode":"US19403900","setting_14":1}},
{"type":"Feature","geometry":{"type":"Point","coordinates":[-81.1502,35.2372]},"properties":{"educationprogramcode":"US19403900","setting_14":1}},
{"type":"Feature","geometry":{"type":"Point","coordinates":[-81.133,35.2325]},"properties":{"educationprogramcode":"US19403900","setting_14":1}},
{"type":"Feature","geometry":{"type":"Point","coordinates":[-81.1498,35.234]},"properties":{"educationprogramcode":"US19403900","setting_14":1}},
{"type":"Feature","geometry":{"type":"Point","coordinates":[-81.1515,35.2329]},"properties":{"educationprogramcode":"US19403900","setting_14":7}},
{"type":"Feature","geometry":{"type":"Point","coordinates":[-81.1342,35.2382]},"properties":{"educationprogramcode":"US19403900","setting_14":1}},
{"type":"Feature","geometry":{"type":"Point","coordinates":[-81.1437,35.2351]},"properties":{"educationprogramcode":"US19403900","setting_14":1}},
{"type":"Feature","geometry":{"type":"Point","coordinates":[-81.1388,35.2203]},"properties":{"educationprogramcode":"US19403900","setting_14":1}},
{"type":"Feature","geometry":{"type":"Point","coordinates":[-81.15,35.2319]},"properties":{"educationprogramcode":"US19403900","setting_14":1}},
{"type":"Feature","geometry":{"type":"Point","coordinates":[-81.1335,35.2212]},"properties":{"educationprogramcode":"US19403900","setting_14":1}},
{"type":"Feature","geometry":{"type":"Point","coordinates":[-81.1507,35.224]},"properties":{"educationprogramcode":"US19403900","setting_14":6}},
{"type":"Feature","geometry":{"type":"Point","coordinates":[-81.1492,35.2314]},"properties":{"educationprogramcode":"US19403900","setting_14":1}},
{"type":"Feature","geometry":{"type":"Point","coordinates":[-81.1505,35.2285]},"properties":{"educationprogramcode":"US19403900","setting_14":1}},
{"type":"Feature","geometry":{"type":"Point","coordinates":[-81.1406,35.2245]},"properties":{"educationprogramcode":"US19403900","setting_14":1}},
{"type":"Feature","geometry":{"type":"Point","coordinates":[-81.1346,35.2271]},"properties":{"educationprogramcode":"US19403900","setting_14":1}},
{"type":"Feature","geometry":{"type":"Point","coordinates":[-81.1497,35.231]},"properties":{"educationprogramcode":"US19403900","setting_14":1}},
{"type":"Feature","geometry":{"type":"Point","coordinates":[-81.1387,35.2323]},"properties":{"educationprogramcode":"US19403900","setting_14":1}},
{"type":"Feature","geometry":{"type":"Point","coordinates":[-81.1383,35.2317]},"properties":{"educationprogramcode":"US19403900","setting_14":1}},
{"type":"Feature","geometry":{"type":"Point","coordinates":[-81.1435,35.2299]},"properties":{"educationprogramcode":"US19403900","setting_14":6}},
{"type":"Feature","geometry":{"type":"Point","coordinates":[-81.151,35.2392]},"properties":{"educationprogramcode":"US19403900","setting_14":1}},
{"type":"Feature","geometry":{"type":"Point","coordinates":[-81.1485,35.2228]},"properties":{"educationprogramcode":"US19403900","setting_14":2}},
{"type":"Feature","geometry":{"type":"Point","coordinates":[-81.1497,35.207]},"properties":{"educationprogramcode":"US19403900","setting_14":1}},
{"type":"Feature","geometry":{"type":"Point","coordinates":[-81.1496,35.2119]},"properties":{"educationprogramcode":"US19403900","setting_14":6}},
{"type":"Feature","geometry":{"type":"Point","coordinates":[-81.1425,35.2062]},"properties":{"educationprogramcode":"US19403900","setting_14":1}},
{"type":"Feature","geometry":{"type":"Point","coordinates":[-81.1505,35.2107]},"properties":{"educationprogramcode":"US19403900","setting_14":1}},
{"type":"Feature","geometry":{"type":"Point","coordinates":[-81.1446,35.2084]},"properties":{"educationprogramcode":"US19403900","setting_14":-9}},
{"type":"Feature","geometry":{"type":"Point","coordinates":[-81.1423,35.2078]},"properties":{"educationprogramcode":"US19403900","setting_14":1}},
{"type":"Feature","geometry":{"type":"Point","coordinates":[-81.1442,35.2075]},"properties":{"educationprogramcode":"US19403900","setting_14":1}},
{"type":"Feature","geometry":{"type":"Point","coordinates":[-81.1415,35.2126]},"properties":{"educationprogramcode":"US19403900","setting_14":1}},
{"type":"Feature","geometry":{"type":"Point","coordinates":[-81.1439,35.2088]},"properties":{"educationprogramcode":"US19403900","setting_14":1}},
{"type":"Feature","geometry":{"type":"Point","coordinates":[-81.1454,35.2137]},"properties":{"educationprogramcode":"US19403900","setting_14":1}},
{"type":"Feature","geometry":{"type":"Point","coordinates":[-80.8467,35.4117]},"properties":{"educationprogramcode":"US19403900","setting_14":-9}},
{"type":"Feature","geometry":{"type":"Point","coordinates":[-81.3645,35.2517]},"properties":{"educationprogramcode":"US19403900","setting_14":11}},
{"type":"Feature","geometry":{"type":"Point","coordinates":[-81.3674,35.2506]},"properties":{"educationprogramcode":"US19403900","setting_14":1}},
{"type":"Feature","geometry":{"type":"Point","coordinates":[-81.3619,35.2438]},"properties":{"educationprogramcode":"US19403900","setting_14":1}},
{"type":"Feature","geometry":{"type":"Point","coordinates":[-81.367,35.2476]},"properties":{"educationprogramcode":"US19403900","setting_14":-9}},
{"type":"Feature","geometry":{"type":"Point","coordinates":[-81.3569,35.2435]},"properties":{"educationprogramcode":"US19403900","setting_14":1}},
{"type":"Feature","geometry":{"type":"Point","coordinates":[-81.3573,35.25]},"properties":{"educationprogramcode":"US19403900","setting_14":1}},
{"type":"Feature","geometry":{"type":"Point","coordinates":[-81.3675,35.2529]},"properties":{"educationprogramcode":"US19403900","setting_14":1}},
{"type":"Feature","geometry":{"type":"Point","coordinates":[-81.3633,35.2423]},"properties":{"educationprogramcode":"US19403900","setting_14":1}},
{"type":"Feature","geometry":{"type":"Point","coordinates":[-81.3645,35.2529]},"properties":{"educationprogramcode":"US19403900","setting_14":-9}},
{"type":"Feature","geometry":{"type":"Point","coordinates":[-81.3625,35.2478]},"properties":{"educationprogramcode":"US19403900","setting_14":1}},
{"type":"Feature","geometry":{"type":"Point","coordinates":[-81.3592,35.2426]},"properties":{"educationprogramcode":"US19403900","setting_14":1}},
{"type":"Feature","geometry":{"type":"Point","coordinates":[-81.3664,35.2496]},"properties":{"educationprogramcode":"US19403900","setting_14":1}},
{"type":"Feature","geometry":{"type":"Point","coordinates":[-81.3576,35.2415]},"properties":{"educationprogramcode":"US19403900","setting_14":10}},
{"type":"Feature","geometry":{"type":"Point","coordinates":[-81.2279,35.4812]},"properties":{"educationprogramcode":"US19403900","setting_14":1}},
{"type":"Feature","geometry":{"type":"Point","coordinates":[-81.2308,35.4817]},"properties":{"educationprogramcode":"US19403900","setting_14":6}},
{"type":"Feature","geometry":{"type":"Point","coordinates":[-81.2282,35.4826]},"properties":{"educationprogramcode":"US19403900","setting_14":1}},
{"type":"Feature","geometry":{"type":"Point","coordinates":[-81.2224,35.48]},"properties":{"educationprogramcode":"US19403900","setting_14":6}},
{"type":"Feature","geometry":{"type":"Point","coordinates":[-81.229,35.4809]},"properties":{"educationprogramcode":"US19403900","setting_14":6}},
{"type":"Feature","geometry":{"type":"Point","coordinates":[-81.227,35.4869]},"properties":{"educationprogramcode":"US19403900","setting_14":1}},
{"type":"Feature","geometry":{"type":"Point","coordinates":[-81.2303,35.4799]},"properties":{"educationprogramcode":"US19403900","setting_14":1}},
{"type":"Feature","geometry":{"type":"Point","coordinates":[-81.2186,35.4886]},"properties":{"educationprogramcode":"US19403900","setting_14":1}},
{"type":"Feature","geometry":{"type":"Point","coordinates":[-81.2235,35.491]},"properties":{"educationprogramcode":"US19403900","setting_14":6}},
{"type":"Feature","geometry":{"type":"Point","coordinates":[-81.2223,35.4908]},"properties":{"educationprogramcode":"US19403900","setting_14":1}},
{"type":"Feature","geometry":{"type":"Point","coordinates":[-81.2212,35.485]},"properties":{"educationprogramcode":"US19403900","setting_14":6}},
{"type":"Feature","geometry":{"type":"Point","coordinates":[-81.2252,35.4822]},"properties":{"educationprogramcode":"US19403900","setting_14":2}},
{"type":"Feature","geometry":{"type":"Point","coordinates":[-81.2186,35.4831]},"properties":{"educationprogramcode":"US19403900","setting_14":6}},
{"type":"Feature","geometry":{"type":"Point","coordinates":[-81.2182,35.4805]},"properties":{"educationprogramcode":"US19403900","setting_14":1}},
{"type":"Feature","geometry":{"type":"Point","coordinates":[-80.6923,35.1128]},"properties":{"educationprogramcode":"US19403900","setting_14":1}},
{"type":"Feature","geometry":{"type":"Point","coordinates":[-80.6897,35.1084]},"properties":{"educationprogramcode":"US19403900","setting_14":6}},
{"type":"Feature","geometry":{"type":"Point","coordinates":[-80.6973,35.1201]},"properties":{"educationprogramcode":"US19403900","setting_14":1}},
{"type":"Feature","geometry":{"type":"Point","coordinates":[-80.6883,35.1101]},"properties":{"educationprogramcode":"US19403900","setting_14":6}},
{"type":"Feature","geometry":{"type":"Point","coordinates":[-80.5444,34.9378]},"properties":{"educationprogramcode":"US19403900","setting_14":1}},
{"type":"Feature","geometry":{"type":"Point","coordinates":[-80.8076,35.5891]},"properties":{"educationprogramcode":"US19403900","setting_14":1}},
{"type":"Feature","geometry":{"type":"Point","coordinates":[-80.8152,35.5835]},"properties":{"educationprogramcode":"US19403900","setting_14":2}},
{"type":"Feature","geometry":{"type":"Point","coordinates":[-81.0309,35.3102]},"properties":{"educationprogramcode":"US19403900","setting_14":1}},
{"type":"Feature","geometry":{"type":"Point","coordinates":[-81.0299,35.3074]},"properties":{"educationprogramcode":"US19403900","setting_14":1}},
{"type":"Feature","geometry":{"type":"Point","coordinates":[-81.9833,35.3731]},"properties":{"educationprogramcode":"US19403900","setting_14":1}},
{"type":"Feature","geometry":{"type":"Point","coordinates":[-81.5526,35.3105]},"properties":{"educationprogramcode":"US19403900","setting_14":1}},
{"type":"Feature","geometry":{"type":"Point","coordinates":[-81.5461,35.3047]},"properties":{"educationprogramcode":"US19403900","setting_14":1}},
{"type":"Feature","geometry":{"type":"Point","coordinates":[-81.5478,35.3061]},"properties":{"educationprogramcode":"US19403900","setting_14":1}},
{"type":"Feature","geometry":{"type":"Point","coordinates":[-81.5565,35.3035]},"properties":{"educationprogramcode":"US19403900","setting_14":1}},
{"type":"Feature","geometry":{"type":"Point","coordinates":[-81.5575,35.3051]},"properties":{"educationprogramcode":"US19403900","setting_14":1}},
{"type":"Feature","geometry":{"type":"Point","coordinates":[-81.554,35.3116]},"properties":{"educationprogramcode":"US19403900","setting_14":1}},
{"type":"Feature","geometry":{"type":"Point","coordinates":[-81.5508,35.3032]},"properties":{"educationprogramcode":"US19403900","setting_14":1}},
{"type":"Feature","geometry":{"type":"Point","coordinates":[-81.5577,35.298]},"properties":{"educationprogramcode":"US19403900","setting_14":1}},
{"type":"Feature","geometry":{"type":"Point","coordinates":[-81.5512,35.2986]},"properties":{"educationprogramcode":"US19403900","setting_14":1}},
{"type":"Feature","geometry":{"type":"Point","coordinates":[-81.5539,35.3048]},"properties":{"educationprogramcode":"US19403900","setting_14":1}},
{"type":"Feature","geometry":{"type":"Point","coordinates":[-81.551,35.3092]},"properties":{"educationprogramcode":"US19403900","setting_14":1}},
{"type":"Feature","geometry":{"type":"Point","coordinates":[-81.5481,35.3046]},"properties":{"educationprogramcode":"US19403900","setting_14":1}},
{"type":"Feature","geometry":{"type":"Point","coordinates":[-81.5492,35.3081]},"properties":{"educationprogramcode":"US19403900","setting_14":1}},
{"type":"Feature","geometry":{"type":"Point","coordinates":[-81.5523,35.306]},"properties":{"educationprogramcode":"US19403900","setting_14":1}},
{"type":"Feature","geometry":{"type":"Point","coordinates":[-81.5533,35.31]},"properties":{"educationprogramcode":"US19403900","setting_14":1}},
{"type":"Feature","geometry":{"type":"Point","coordinates":[-81.5511,35.3014]},"properties":{"educationprogramcode":"US19403900","setting_14":1}},
{"type":"Feature","geometry":{"type":"Point","coordinates":[-81.5523,35.3055]},"properties":{"educationprogramcode":"US19403900","setting_14":1}},
{"type":"Feature","geometry":{"type":"Point","coordinates":[-81.103,35.3527]},"properties":{"educationprogramcode":"US19403900","setting_14":6}},
{"type":"Feature","geometry":{"type":"Point","coordinates":[-81.0998,35.3515]},"properties":{"educationprogramcode":"US19403900","setting_14":6}},
{"type":"Feature","geometry":{"type":"Point","coordinates":[-81.1006,35.3529]},"properties":{"educationprogramcode":"US19403900","setting_14":6}},
{"type":"Feature","geometry":{"type":"Point","coordinates":[-81.1016,35.3521]},"properties":{"educationprogramcode":"US19403900","setting_14":1}},
{"type":"Feature","geometry":{"type":"Point","coordinates":[-81.1008,35.3502]},"properties":{"educationprogramcode":"US19403900","setting_14":6}},
{"type":"Feature","geometry":{"type":"Point","coordinates":[-81.1038,35.3521]},"properties":{"educationprogramcode":"US19403900","setting_14":6}},
{"type":"Feature","geometry":{"type":"Point","coordinates":[-81.0986,35.3504]},"properties":{"educationprogramcode":"US19403900","setting_14":6}},
{"type":"Feature","geometry":{"type":"Point","coordinates":[-81.1004,35.3564]},"properties":{"educationprogramcode":"US19403900","setting_14":6}},
{"type":"Feature","geometry":{"type":"Point","coordinates":[-80.0724,34.9639]},"properties":{"educationprogramcode":"US19403900","setting_14":1}},
{"type":"Feature","geometry":{"type":"Point","coordinates":[-80.7374,34.9245]},"properties":{"educationprogramcode":"US19403900","setting_14":6}},
{"type":"Feature","geometry":{"type":"Point","coordinates":[-80.8701,35.2031]},"properties":{"educationprogramcode":"US19403900","setting_14":1}},
{"type":"Feature","geometry":{"type":"Point","coordinates":[-80.8528,35.2191]},"properties":{"educationprogramcode":"US19403900","setting_14":11}},
{"type":"Feature","geometry":{"type":"Point","coordinates":[-80.8708,35.2156]},"properties":{"educationprogramcode":"US19403900","setting_14":1}},
{"type":"Feature","geometry":{"type":"Point","coordinates":[-80.8644,35.2187]},"properties":{"educationprogramcode":"US19403900","setting_14":1}},
{"type":"Feature","geometry":{"type":"Point","coordinates":[-80.8563,35.2133]},"properties":{"educationprogramcode":"US19403900","setting_14":1}},
{"type":"Feature","geometry":{"type":"Point","coordinates":[-80.8524,35.2132]},"properties":{"educationprogramcode":"US19403900","setting_14":1}},
{"type":"Feature","geometry":{"type":"Point","coordinates":[-80.8714,35.2153]},"properties":{"educationprogramcode":"US19403900","setting_14":1}},
{"type":"Feature","geometry":{"type":"Point","coordinates":[-80.8324,35.221]},"properties":{"educationprogramcode":"US19403900","setting_14":1}},
{"type":"Feature","geometry":{"type":"Point","coordinates":[-80.8356,35.2095]},"properties":{"educationprogramcode":"US19403900","setting_14":1}},
{"type":"Feature","geometry":{"type":"Point","coordinates":[-80.8319,35.2108]},"properties":{"educationprogramcode":"US19403900","setting_14":11}},
{"type":"Feature","geometry":{"type":"Point","coordinates":[-80.8319,35.2215]},"properties":{"educationprogramcode":"US19403900","setting_14":2}},
{"type":"Feature","geometry":{"type":"Point","coordinates":[-80.8287,35.22]},"properties":{"educationprogramcode":"US19403900","setting_14":1}},
{"type":"Feature","geometry":{"type":"Point","coordinates":[-80.831,35.2189]},"properties":{"educationprogramcode":"US19403900","setting_14":1}},
{"type":"Feature","geometry":{"type":"Point","coordinates":[-80.8358,35.2148]},"properties":{"educationprogramcode":"US19403900","setting_14":1}},
{"type":"Feature","geometry":{"type":"Point","coordinates":[-80.8262,35.2205]},"properties":{"educationprogramcode":"US19403900","setting_14":1}},
{"type":"Feature","geometry":{"type":"Point","coordinates":[-80.7878,35.2231]},"properties":{"educationprogramcode":"US19403900","setting_14":1}},
{"type":"Feature","geometry":{"type":"Point","coordinates":[-80.8349,35.2]},"properties":{"educationprogramcode":"US19403900","setting_14":1}},
{"type":"Feature","geometry":{"type":"Point","coordinates":[-80.834,35.1949]},"properties":{"educationprogramcode":"US19403900","setting_14":1}},
{"type":"Feature","geometry":{"type":"Point","coordinates":[-80.8317,35.2004]},"properties":{"educationprogramcode":"US19403900","setting_14":1}},
{"type":"Feature","geometry":{"type":"Point","coordinates":[-80.836,35.2006]},"properties":{"educationprogramcode":"US19403900","setting_14":1}},
{"type":"Feature","geometry":{"type":"Point","coordinates":[-80.8338,35.202]},"properties":{"educationprogramcode":"US19403900","setting_14":1}},
{"type":"Feature","geometry":{"type":"Point","coordinates":[-80.8345,35.1966]},"properties":{"educationprogramcode":"US19403900","setting_14":1}},
{"type":"Feature","geometry":{"type":"Point","coordinates":[-80.904,35.2352]},"properties":{"educationprogramcode":"US19403900","setting_14":1}},
{"type":"Feature","geometry":{"type":"Point","coordinates":[-80.8562,35.1757]},"properties":{"educationprogramcode":"US19403900","setting_14":7}},
{"type":"Feature","geometry":{"type":"Point","coordinates":[-80.8659,35.1298]},"properties":{"educationprogramcode":"US19403900","setting_14":1}},
{"type":"Feature","geometry":{"type":"Point","coordinates":[-80.8605,35.137]},"properties":{"educationprogramcode":"US19403900","setting_14":6}},
{"type":"Feature","geometry":{"type":"Point","coordinates":[-80.8667,35.1254]},"properties":{"educationprogramcode":"US19403900","setting_14":1}},
{"type":"Feature","geometry":{"type":"Point","coordinates":[-80.8581,35.1278]},"properties":{"educationprogramcode":"US19403900","setting_14":1}},
{"type":"Feature","geometry":{"type":"Point","coordinates":[-80.8665,35.141]},"properties":{"educationprogramcode":"US19403900","setting_14":6}},
{"type":"Feature","geometry":{"type":"Point","coordinates":[-80.8556,35.1376]},"properties":{"educationprogramcode":"US19403900","setting_14":1}},
{"type":"Feature","geometry":{"type":"Point","coordinates":[-80.8669,35.1284]},"properties":{"educationprogramcode":"US19403900","setting_14":1}},
{"type":"Feature","geometry":{"type":"Point","coordinates":[-80.8526,35.1352]},"properties":{"educationprogramcode":"US19403900","setting_14":7}},
{"type":"Feature","geometry":{"type":"Point","coordinates":[-80.787,35.1604]},"properties":{"educationprogramcode":"US19403900","setting_14":6}},
{"type":"Feature","geometry":{"type":"Point","coordinates":[-80.8803,35.2832]},"properties":{"educationprogramcode":"US19403900","setting_14":12}},
{"type":"Feature","geometry":{"type":"Point","coordinates":[-80.8031,35.1108]},"properties":{"educationprogramcode":"US19403900","setting_14":7}},
{"type":"Feature","geometry":{"type":"Point","coordinates":[-80.8259,35.2191]},"properties":{"educationprogramcode":"US19403900","setting_14":1}},
{"type":"Feature","geometry":{"type":"Point","coordinates":[-80.8241,35.2151]},"properties":{"educationprogramcode":"US19403900","setting_14":1}},
{"type":"Feature","geometry":{"type":"Point","coordinates":[-80.7427,35.3209]},"properties":{"educationprogramcode":"US19403900","setting_14":7}},
{"type":"Feature","geometry":{"type":"Point","coordinates":[-80.7407,35.3226]},"properties":{"educationprogramcode":"US19403900","setting_14":6}},
{"type":"Feature","geometry":{"type":"Point","coordinates":[-80.7343,35.3205]},"properties":{"educationprogramcode":"US19403900","setting_14":1}},
{"type":"Feature","geometry":{"type":"Point","coordinates":[-80.7432,35.3137]},"properties":{"educationprogramcode":"US19403900","setting_14":4}},
{"type":"Feature","geometry":{"type":"Point","coordinates":[-80.9421,35.1356]},"properties":{"educationprogramcode":"US19403900","setting_14":13}},
{"type":"Feature","geometry":{"type":"Point","coordinates":[-78.7917,34.5288]},"properties":{"educationprogramcode":"US19403900","setting_14":11}},
{"type":"Feature","geometry":{"type":"Point","coordinates":[-77.942,34.2264]},"properties":{"educationprogramcode":"US19403900","setting_14":1}},
{"type":"Feature","geometry":{"type":"Point","coordinates":[-77.9326,34.2265]},"properties":{"educationprogramcode":"US19403900","setting_14":1}},
{"type":"Feature","geometry":{"type":"Point","coordinates":[-77.8833,34.2082]},"properties":{"educationprogramcode":"US19403900","setting_14":1}},
{"type":"Feature","geometry":{"type":"Point","coordinates":[-81.3268,35.7527]},"properties":{"educationprogramcode":"US19403900","setting_14":1}},
{"type":"Feature","geometry":{"type":"Point","coordinates":[-81.3232,35.7469]},"properties":{"educationprogramcode":"US19403900","setting_14":1}},
{"type":"Feature","geometry":{"type":"Point","coordinates":[-81.3296,35.7486]},"properties":{"educationprogramcode":"US19403900","setting_14":1}},
{"type":"Feature","geometry":{"type":"Point","coordinates":[-81.3261,35.7495]},"properties":{"educationprogramcode":"US19403900","setting_14":1}},
{"type":"Feature","geometry":{"type":"Point","coordinates":[-81.378,35.6609]},"properties":{"educationprogramcode":"US19403900","setting_14":2}},
{"type":"Feature","geometry":{"type":"Point","coordinates":[-81.3739,35.6572]},"properties":{"educationprogramcode":"US19403900","setting_14":3}},
{"type":"Feature","geometry":{"type":"Point","coordinates":[-81.3717,35.6544]},"properties":{"educationprogramcode":"US19403900","setting_14":11}},
{"type":"Feature","geometry":{"type":"Point","coordinates":[-81.3723,35.6611]},"properties":{"educationprogramcode":"US19403900","setting_14":1}},
{"type":"Feature","geometry":{"type":"Point","coordinates":[-81.5336,35.9508]},"properties":{"educationprogramcode":"US19403900","setting_14":1}},
{"type":"Feature","geometry":{"type":"Point","coordinates":[-81.7142,35.7349]},"properties":{"educationprogramcode":"US19403900","setting_14":11}},
{"type":"Feature","geometry":{"type":"Point","coordinates":[-81.2309,35.6545]},"properties":{"educationprogramcode":"US19403900","setting_14":7}},
{"type":"Feature","geometry":{"type":"Point","coordinates":[-81.2363,35.6562]},"properties":{"educationprogramcode":"US19403900","setting_14":11}},
{"type":"Feature","geometry":{"type":"Point","coordinates":[-80.9026,35.8502]},"properties":{"educationprogramcode":"US19403900","setting_14":11}},
{"type":"Feature","geometry":{"type":"Point","coordinates":[-82.4982,35.3485]},"properties":{"educationprogramcode":"US19403900","setting_14":1}},
{"type":"Feature","geometry":{"type":"Point","coordinates":[-82.5148,35.5557]},"properties":{"educationprogramcode":"US19403900","setting_14":1}}
]}