{"type":"FeatureCollection", "features": [
{"type":"Feature","geometry":{"type":"Point","coordinates":[-80.3182,36.0564]},"properties":{"educationprogramcode":"US19504600","setting_14":1}},
{"type":"Feature","geometry":{"type":"Point","coordinates":[-79.7627,36.0622]},"properties":{"educationprogramcode":"US19504600","setting_14":1}},
{"type":"Feature","geometry":{"type":"Point","coordinates":[-79.766,36.0747]},"properties":{"educationprogramcode":"US19504600","setting_14":1}},
{"type":"Feature","geometry":{"type":"Point","coordinates":[-78.8173,35.399]},"properties":{"educationprogramcode":"US19504600","setting_14":1}},
{"type":"Feature","geometry":{"type":"Point","coordinates":[-78.817,35.395]},"properties":{"educationprogramcode":"US19504600","setting_14":1}},
{"type":"Feature","geometry":{"type":"Point","coordinates":[-78.5726,35.7602]},"properties":{"educationprogramcode":"US19504600","setting_14":1}},
{"type":"Feature","geometry":{"type":"Point","coordinates":[-78.6288,35.9405]},"properties":{"educationprogramcode":"US19504600","setting_14":11}},
{"type":"Feature","geometry":{"type":"Point","coordinates":[-78.5298,35.8648]},"properties":{"educationprogramcode":"US19504600","setting_14":11}},
{"type":"Feature","geometry":{"type":"Point","coordinates":[-78.9236,36.0895]},"properties":{"educationprogramcode":"US19504600","setting_14":1}},
{"type":"Feature","geometry":{"type":"Point","coordinates":[-77.9186,35.7246]},"properties":{"educationprogramcode":"US19504600","setting_14":1}},
{"type":"Feature","geometry":{"type":"Point","coordinates":[-80.5524,35.0124]},"properties":{"educationprogramcode":"US19504600","setting_14":1}},
{"type":"Feature","geometry":{"type":"Point","coordinates":[-80.0687,34.964]},"properties":{"educationprogramcode":"US19504600","setting_14":6}},
{"type":"Feature","geometry":{"type":"Point","coordinates":[-80.7396,34.9318]},"properties":{"educationprogramcode":"US19504600","setting_14":1}},
{"type":"Feature","geometry":{"type":"Point","coordinates":[-78.8665,35.0622]},"properties":{"educationprogramcode":"US19504600","setting_14":3}},
{"type":"Feature","geometry":{"type":"Point","coordinates":[-78.8662,35.0674]},"properties":{"educationprogramcode":"US19504600","setting_14":1}},
{"type":"Feature","geometry":{"type":"Point","coordinates":[-78.9304,35.033]},"properties":{"educationprogramcode":"US19504600","setting_14":1}},
{"type":"Feature","geometry":{"type":"Point","coordinates":[-78.9592,35.0832]},"properties":{"educationprogramcode":"US19504600","setting_14":-9}},
{"type":"Feature","geometry":{"type":"Point","coordinates":[-78.9672,35.0201]},"properties":{"educationprogramcode":"US19504600","setting_14":1}},
{"type":"Feature","geometry":{"type":"Point","coordinates":[-78.9786,35.021]},"properties":{"educationprogramcode":"US19504600","setting_14":1}},
{"type":"Feature","geometry":{"type":"Point","coordinates":[-78.9665,35.0325]},"properties":{"educationprogramcode":"US19504600","setting_14":1}},
{"type":"Feature","geometry":{"type":"Point","coordinates":[-78.975,35.0398]},"properties":{"educationprogramcode":"US19504600","setting_14":1}},
{"type":"Feature","geometry":{"type":"Point","coordinates":[-78.9786,35.034]},"properties":{"educationprogramcode":"US19504600","setting_14":1}},
{"type":"Feature","geometry":{"type":"Point","coordinates":[-78.9767,35.0401]},"properties":{"educationprogramcode":"US19504600","setting_14":1}},
{"type":"Feature","geometry":{"type":"Point","coordinates":[-78.9755,35.0304]},"properties":{"educationprogramcode":"US19504600","setting_14":1}},
{"type":"Feature","geometry":{"type":"Point","coordinates":[-78.9797,35.0306]},"properties":{"educationprogramcode":"US19504600","setting_14":1}},
{"type":"Feature","geometry":{"type":"Point","coordinates":[-78.9667,35.0227]},"properties":{"educationprogramcode":"US19504600","setting_14":1}},
{"type":"Feature","geometry":{"type":"Point","coordinates":[-78.982,35.0246]},"properties":{"educationprogramcode":"US19504600","setting_14":1}},
{"type":"Feature","geometry":{"type":"Point","coordinates":[-78.9785,35.0235]},"properties":{"educationprogramcode":"US19504600","setting_14":1}},
{"type":"Feature","geometry":{"type":"Point","coordinates":[-78.9697,35.0304]},"properties":{"educationprogramcode":"US19504600","setting_14":1}},
{"type":"Feature","geometry":{"type":"Point","coordinates":[-78.9677,35.0256]},"properties":{"educationprogramcode":"US19504600","setting_14":1}},
{"type":"Feature","geometry":{"type":"Point","coordinates":[-78.9795,35.0389]},"properties":{"educationprogramcode":"US19504600","setting_14":1}},
{"type":"Feature","geometry":{"type":"Point","coordinates":[-78.9654,35.0226]},"properties":{"educationprogramcode":"US19504600","setting_14":1}},
{"type":"Feature","geometry":{"type":"Point","coordinates":[-78.9678,35.0195]},"properties":{"educationprogramcode":"US19504600","setting_14":1}},
{"type":"Feature","geometry":{"type":"Point","coordinates":[-78.9616,35.0332]},"properties":{"educationprogramcode":"US19504600","setting_14":1}},
{"type":"Feature","geometry":{"type":"Point","coordinates":[-78.9795,35.024]},"properties":{"educationprogramcode":"US19504600","setting_14":1}},
{"type":"Feature","geometry":{"type":"Point","coordinates":[-78.9805,35.0272]},"properties":{"educationprogramcode":"US19504600","setting_14":1}},
{"type":"Feature","geometry":{"type":"Point","coordinates":[-78.9777,35.0281]},"properties":{"educationprogramcode":"US19504600","setting_14":1}},
{"type":"Feature","geometry":{"type":"Point","coordinates":[-78.9743,35.0289]},"properties":{"educationprogramcode":"US19504600","setting_14":1}},
{"type":"Feature","geometry":{"type":"Point","coordinates":[-78.9697,35.0216]},"properties":{"educationprogramcode":"US19504600","setting_14":1}},
{"type":"Feature","geometry":{"type":"Point","coordinates":[-78.9977,35.1408]},"properties":{"educationprogramcode":"US19504600","setting_14":2}},
{"type":"Feature","geometry":{"type":"Point","coordinates":[-78.9979,35.1391]},"properties":{"educationprogramcode":"US19504600","setting_14":1}},
{"type":"Feature","geometry":{"type":"Point","coordinates":[-79.0011,35.1366]},"properties":{"educationprogramcode":"US19504600","setting_14":1}},
{"type":"Feature","geometry":{"type":"Point","coordinates":[-78.9985,35.1366]},"properties":{"educationprogramcode":"US19504600","setting_14":1}},
{"type":"Feature","geometry":{"type":"Point","coordinates":[-78.9984,35.1383]},"properties":{"educationprogramcode":"US19504600","setting_14":1}},
{"type":"Feature","geometry":{"type":"Point","coordinates":[-79,35.1404]},"properties":{"educationprogramcode":"US19504600","setting_14":1}},
{"type":"Feature","geometry":{"type":"Point","coordinates":[-78.897,35.1316]},"properties":{"educationprogramcode":"US19504600","setting_14":-9}},
{"type":"Feature","geometry":{"type":"Point","coordinates":[-78.8948,35.1303]},"properties":{"educationprogramcode":"US19504600","setting_14":1}},
{"type":"Feature","geometry":{"type":"Point","coordinates":[-79.0079,35.0582]},"properties":{"educationprogramcode":"US19504600","setting_14":1}},
{"type":"Feature","geometry":{"type":"Point","coordinates":[-79.0004,35.0628]},"properties":{"educationprogramcode":"US19504600","setting_14":1}},
{"type":"Feature","geometry":{"type":"Point","coordinates":[-79.4247,35.1435]},"properties":{"educationprogramcode":"US19504600","setting_14":6}},
{"type":"Feature","geometry":{"type":"Point","coordinates":[-78.5748,34.6217]},"properties":{"educationprogramcode":"US19504600","setting_14":1}},
{"type":"Feature","geometry":{"type":"Point","coordinates":[-79.7042,34.8874]},"properties":{"educationprogramcode":"US19504600","setting_14":6}},
{"type":"Feature","geometry":{"type":"Point","coordinates":[-78.9414,34.9672]},"properties":{"educationprogramcode":"US19504600","setting_14":1}},
{"type":"Feature","geometry":{"type":"Point","coordinates":[-78.9468,34.9689]},"properties":{"educationprogramcode":"US19504600","setting_14":1}},
{"type":"Feature","geometry":{"type":"Point","coordinates":[-79.4634,34.7685]},"properties":{"educationprogramcode":"US19504600","setting_14":-9}},
{"type":"Feature","geometry":{"type":"Point","coordinates":[-79.4659,34.7716]},"properties":{"educationprogramcode":"US19504600","setting_14":1}},
{"type":"Feature","geometry":{"type":"Point","coordinates":[-79.0085,34.6269]},"properties":{"educationprogramcode":"US19504600","setting_14":1}},
{"type":"Feature","geometry":{"type":"Point","coordinates":[-78.9994,34.6269]},"properties":{"educationprogramcode":"US19504600","setting_14":1}},
{"type":"Feature","geometry":{"type":"Point","coordinates":[-79.0055,34.6368]},"properties":{"educationprogramcode":"US19504600","setting_14":1}},
{"type":"Feature","geometry":{"type":"Point","coordinates":[-79.0005,34.6281]},"properties":{"educationprogramcode":"US19504600","setting_14":1}},
{"type":"Feature","geometry":{"type":"Point","coordinates":[-79.0042,34.6299]},"properties":{"educationprogramcode":"US19504600","setting_14":11}},
{"type":"Feature","geometry":{"type":"Point","coordinates":[-79.0123,34.6247]},"properties":{"educationprogramcode":"US19504600","setting_14":1}},
{"type":"Feature","geometry":{"type":"Point","coordinates":[-79.0051,34.6317]},"properties":{"educationprogramcode":"US19504600","setting_14":1}},
{"type":"Feature","geometry":{"type":"Point","coordinates":[-79.0097,34.631]},"properties":{"educationprogramcode":"US19504600","setting_14":1}},
{"type":"Feature","geometry":{"type":"Point","coordinates":[-79.0075,34.622]},"properties":{"educationprogramcode":"US19504600","setting_14":1}},
{"type":"Feature","geometry":{"type":"Point","coordinates":[-79.0133,34.624]},"properties":{"educationprogramcode":"US19504600","setting_14":1}},
{"type":"Feature","geometry":{"type":"Point","coordinates":[-78.9998,34.6233]},"properties":{"educationprogramcode":"US19504600","setting_14":1}},
{"type":"Feature","geometry":{"type":"Point","coordinates":[-79.0019,34.6363]},"properties":{"educationprogramcode":"US19504600","setting_14":1}},
{"type":"Feature","geometry":{"type":"Point","coordinates":[-79.0115,34.6369]},"properties":{"educationprogramcode":"US19504600","setting_14":1}},
{"type":"Feature","geometry":{"type":"Point","coordinates":[-79.014,34.6272]},"properties":{"educationprogramcode":"US19504600","setting_14":1}},
{"type":"Feature","geometry":{"type":"Point","coordinates":[-79.0117,34.6314]},"properties":{"educationprogramcode":"US19504600","setting_14":1}},
{"type":"Feature","geometry":{"type":"Point","coordinates":[-79.0034,34.6369]},"properties":{"educationprogramcode":"US19504600","setting_14":1}},
{"type":"Feature","geometry":{"type":"Point","coordinates":[-79.0144,34.6293]},"properties":{"educationprogramcode":"US19504600","setting_14":1}},
{"type":"Feature","geometry":{"type":"Point","coordinates":[-79.0026,34.6233]},"properties":{"educationprogramcode":"US19504600","setting_14":1}},
{"type":"Feature","geometry":{"type":"Point","coordinates":[-79.0127,34.6277]},"properties":{"educationprogramcode":"US19504600","setting_14":2}},
{"type":"Feature","geometry":{"type":"Point","coordinates":[-79.0085,34.6221]},"properties":{"educationprogramcode":"US19504600","setting_14":1}},
{"type":"Feature","geometry":{"type":"Point","coordinates":[-78.9997,34.6349]},"properties":{"educationprogramcode":"US19504600","setting_14":1}},
{"type":"Feature","geometry":{"type":"Point","coordinates":[-79.0152,34.6267]},"properties":{"educationprogramcode":"US19504600","setting_14":1}},
{"type":"Feature","geometry":{"type":"Point","coordinates":[-79.0093,34.6256]},"properties":{"educationprogramcode":"US19504600","setting_14":1}},
{"type":"Feature","geometry":{"type":"Point","coordinates":[-79.009,34.6247]},"properties":{"educationprogramcode":"US19504600","setting_14":1}},
{"type":"Feature","geometry":{"type":"Point","coordinates":[-79.0136,34.6195]},"properties":{"educationprogramcode":"US19504600","setting_14":1}},
{"type":"Feature","geometry":{"type":"Point","coordinates":[-79.0078,34.623]},"properties":{"educationprogramcode":"US19504600","setting_14":1}},
{"type":"Feature","geometry":{"type":"Point","coordinates":[-79.012,34.6193]},"properties":{"educationprogramcode":"US19504600","setting_14":1}},
{"type":"Feature","geometry":{"type":"Point","coordinates":[-79.0096,34.6192]},"properties":{"educationprogramcode":"US19504600","setting_14":1}},
{"type":"Feature","geometry":{"type":"Point","coordinates":[-79.011,34.6198]},"properties":{"educationprogramcode":"US19504600","setting_14":1}},
{"type":"Feature","geometry":{"type":"Point","coordinates":[-79.0132,34.6186]},"properties":{"educationprogramcode":"US19504600","setting_14":1}},
{"type":"Feature","geometry":{"type":"Point","coordinates":[-79.0123,34.6204]},"properties":{"educationprogramcode":"US19504600","setting_14":1}},
{"type":"Feature","geometry":{"type":"Point","coordinates":[-79.0043,34.8996]},"properties":{"educationprogramcode":"US19504600","setting_14":-9}},
{"type":"Feature","geometry":{"type":"Point","coordinates":[-79.1957,34.6805]},"properties":{"educationprogramcode":"US19504600","setting_14":1}},
{"type":"Feature","geometry":{"type":"Point","coordinates":[-79.4744,35.1909]},"properties":{"educationprogramcode":"US19504600","setting_14":1}},
{"type":"Feature","geometry":{"type":"Point","coordinates":[-79.4714,35.1889]},"properties":{"educationprogramcode":"US19504600","setting_14":1}},
{"type":"Feature","geometry":{"type":"Point","coordinates":[-79.4644,35.1843]},"properties":{"educationprogramcode":"US19504600","setting_14":-9}},
{"type":"Feature","geometry":{"type":"Point","coordinates":[-79.4753,35.1849]},"properties":{"educationprogramcode":"US19504600","setting_14":1}},
{"type":"Feature","geometry":{"type":"Point","coordinates":[-79.4609,35.1806]},"properties":{"educationprogramcode":"US19504600","setting_14":1}},
{"type":"Feature","geometry":{"type":"Point","coordinates":[-79.4712,35.1886]},"properties":{"educationprogramcode":"US19504600","setting_14":1}},
{"type":"Feature","geometry":{"type":"Point","coordinates":[-79.473,35.1783]},"properties":{"educationprogramcode":"US19504600","setting_14":1}},
{"type":"Feature","geometry":{"type":"Point","coordinates":[-79.208,34.9808]},"properties":{"educationprogramcode":"US19504600","setting_14":1}},
{"type":"Feature","geometry":{"type":"Point","coordinates":[-79.2048,34.9871]},"properties":{"educationprogramcode":"US19504600","setting_14":1}},
{"type":"Feature","geometry":{"type":"Point","coordinates":[-79.2014,34.987]},"properties":{"educationprogramcode":"US19504600","setting_14":1}},
{"type":"Feature","geometry":{"type":"Point","coordinates":[-79.2037,34.9813]},"properties":{"educationprogramcode":"US19504600","setting_14":1}},
{"type":"Feature","geometry":{"type":"Point","coordinates":[-78.9729,34.8035]},"properties":{"educationprogramcode":"US19504600","setting_14":4}},
{"type":"Feature","geometry":{"type":"Point","coordinates":[-77.944,34.2178]},"properties":{"educationprogramcode":"US19504600","setting_14":1}},
{"type":"Feature","geometry":{"type":"Point","coordinates":[-78.6989,34.3331]},"properties":{"educationprogramcode":"US19504600","setting_14":1}},
{"type":"Feature","geometry":{"type":"Point","coordinates":[-81.3724,35.6597]},"properties":{"educationprogramcode":"US19504600","setting_14":1}}
]}